flakely.py
flakely-2024.1.31.dist-info/WHEEL
flakely-2024.1.31.dist-info/METADATA
flakely-2024.1.31.dist-info/RECORD
