Metadata-Version: 2.1
Name: flakely
Version: 2024.1.31
Summary: Signed snowflake ID's
License: MIT
Author: Zech Zimmerman
Author-email: hi@zech.codes
Requires-Python: >=3.10,<4.0
Classifier: License :: OSI Approved :: MIT License
Classifier: Programming Language :: Python :: 3
Classifier: Programming Language :: Python :: 3.10
Classifier: Programming Language :: Python :: 3.11
